<?xml version="1.0" encoding="iso-8859-1"?>
<a003>
  <LISTA_DADOS_BASICOS>
    <DADOS_BASICOS NUM_SERIE_ELEMENTO_PRIMARIO="20-1-130104" COD_INSTALACAO="10905" COD_TAG_PONTO_MEDICAO="FIT-3115-03">
      <LISTA_CONFIGURACAO_CV>
        <CONFIGURACAO_CV>
          <NUM_SERIE_COMPUTADOR_VAZAO>11905107</NUM_SERIE_COMPUTADOR_VAZAO>
          <DHA_COLETA>31/01/2023 00:12:35</DHA_COLETA>
          <MED_TEMPERATURA>020,00</MED_TEMPERATURA>
          <MED_PRESSAO_ATMSA>101,325</MED_PRESSAO_ATMSA>
          <MED_PRESSAO_RFRNA>101,325</MED_PRESSAO_RFRNA>
          <MED_DENSIDADE_RELATIVA>00,80380830</MED_DENSIDADE_RELATIVA>
          <DSC_NORMA_UTILIZADA_CALCULO>ISO 5167 : 2003</DSC_NORMA_UTILIZADA_CALCULO>
          <PCT_CROMATOGRAFIA_NITROGENIO>001,672000</PCT_CROMATOGRAFIA_NITROGENIO>
          <PCT_CROMATOGRAFIA_CO2>001,071000</PCT_CROMATOGRAFIA_CO2>
          <PCT_CROMATOGRAFIA_METANO>072,349000</PCT_CROMATOGRAFIA_METANO>
          <PCT_CROMATOGRAFIA_ETANO>010,569000</PCT_CROMATOGRAFIA_ETANO>
          <PCT_CROMATOGRAFIA_PROPANO>008,020000</PCT_CROMATOGRAFIA_PROPANO>
          <PCT_CROMATOGRAFIA_N_BUTANO>002,511000</PCT_CROMATOGRAFIA_N_BUTANO>
          <PCT_CROMATOGRAFIA_I_BUTANO>001,839000</PCT_CROMATOGRAFIA_I_BUTANO>
          <PCT_CROMATOGRAFIA_N_PENTANO>000,624000</PCT_CROMATOGRAFIA_N_PENTANO>
          <PCT_CROMATOGRAFIA_I_PENTANO>000,653000</PCT_CROMATOGRAFIA_I_PENTANO>
          <PCT_CROMATOGRAFIA_HEXANO>000,324000</PCT_CROMATOGRAFIA_HEXANO>
          <PCT_CROMATOGRAFIA_HEPTANO>000,106000</PCT_CROMATOGRAFIA_HEPTANO>
          <PCT_CROMATOGRAFIA_OCTANO>000,010000</PCT_CROMATOGRAFIA_OCTANO>
          <PCT_CROMATOGRAFIA_NONANO>000,000000</PCT_CROMATOGRAFIA_NONANO>
          <PCT_CROMATOGRAFIA_DECANO>000,000000</PCT_CROMATOGRAFIA_DECANO>
          <PCT_CROMATOGRAFIA_H2S>000,252000</PCT_CROMATOGRAFIA_H2S>
          <PCT_CROMATOGRAFIA_AGUA>000,000000</PCT_CROMATOGRAFIA_AGUA>
          <PCT_CROMATOGRAFIA_HELIO>000,000000</PCT_CROMATOGRAFIA_HELIO>
          <PCT_CROMATOGRAFIA_OXIGENIO>000,000000</PCT_CROMATOGRAFIA_OXIGENIO>
          <PCT_CROMATOGRAFIA_CO>000,000000</PCT_CROMATOGRAFIA_CO>
          <PCT_CROMATOGRAFIA_HIDROGENIO>000,000000</PCT_CROMATOGRAFIA_HIDROGENIO>
          <PCT_CROMATOGRAFIA_ARGONIO>000,000000</PCT_CROMATOGRAFIA_ARGONIO>
          <DSC_VERSAO_SOFTWARE>27,75,06</DSC_VERSAO_SOFTWARE>
        </CONFIGURACAO_CV>
      </LISTA_CONFIGURACAO_CV>
      <LISTA_ELEMENTO_PRIMARIO>
        <ELEMENTO_PRIMARIO>
          <ICE_LIMITE_SPRR_ALARME>000006,526</ICE_LIMITE_SPRR_ALARME>
          <ICE_LIMITE_INFRR_ALARME>000001,597</ICE_LIMITE_INFRR_ALARME>
          <IND_HABILITACAO_ALARME>S</IND_HABILITACAO_ALARME>
        </ELEMENTO_PRIMARIO>
      </LISTA_ELEMENTO_PRIMARIO>
      <LISTA_INSTRUMENTO_PRESSAO>
        <INSTRUMENTO_PRESSAO>
          <NUM_SERIE>9225001</NUM_SERIE>
          <MED_PRSO_LIMITE_SPRR_ALRME>004050,000</MED_PRSO_LIMITE_SPRR_ALRME>
          <MED_PRSO_LMTE_INFRR_ALRME>000450,000</MED_PRSO_LMTE_INFRR_ALRME>
          <IND_HABILITACAO_ALARME>S</IND_HABILITACAO_ALARME>
          <MED_PRSO_ADOTADA_FALHA>000000,000</MED_PRSO_ADOTADA_FALHA>
          <DSC_ESTADO_INSNO_CASO_FALHA>Use last hour's average on transmitter fail</DSC_ESTADO_INSNO_CASO_FALHA>
          <IND_TIPO_PRESSAO_CONSIDERADA>M</IND_TIPO_PRESSAO_CONSIDERADA>
        </INSTRUMENTO_PRESSAO>
      </LISTA_INSTRUMENTO_PRESSAO>
      <LISTA_INSTRUMENTO_TEMPERATURA>
        <INSTRUMENTO_TEMPERATURA>
          <NUM_SERIE>02470908</NUM_SERIE>
          <MED_TMPTA_SPRR_ALARME>162,00</MED_TMPTA_SPRR_ALARME>
          <MED_TMPTA_INFRR_ALRME>018,00</MED_TMPTA_INFRR_ALRME>
          <IND_HABILITACAO_ALARME>S</IND_HABILITACAO_ALARME>
          <MED_TMPTA_ADTTA_FALHA>026,50</MED_TMPTA_ADTTA_FALHA>
          <DSC_ESTADO_INSTRUMENTO_FALHA>Use last hour's average on transmitter fail</DSC_ESTADO_INSTRUMENTO_FALHA>
        </INSTRUMENTO_TEMPERATURA>
      </LISTA_INSTRUMENTO_TEMPERATURA>
      <LISTA_PLACA_ORIFICIO>
        <PLACA_ORIFICIO>
          <MED_DIAMETRO_REFERENCIA>0054,180</MED_DIAMETRO_REFERENCIA>
          <MED_TEMPERATURA_RFRNA>020,00</MED_TEMPERATURA_RFRNA>
          <DSC_MATERIAL_CONTRUCAO_PLACA>Aco Inox</DSC_MATERIAL_CONTRUCAO_PLACA>
          <MED_DMTRO_INTRO_TRCHO_MDCO>0154,320</MED_DMTRO_INTRO_TRCHO_MDCO>
          <MED_TMPTA_TRCHO_MDCO>020,00</MED_TMPTA_TRCHO_MDCO>
          <DSC_MATERIAL_CNSTO_TRCHO_MDCO>Aco Carbono</DSC_MATERIAL_CNSTO_TRCHO_MDCO>
          <DSC_LCLZO_TMDA_PRSO_DFRNL>Flange Taps</DSC_LCLZO_TMDA_PRSO_DFRNL>
          <IND_TOMADA_PRESSAO_ESTATICA>M</IND_TOMADA_PRESSAO_ESTATICA>
        </PLACA_ORIFICIO>
      </LISTA_PLACA_ORIFICIO>
      <LISTA_INST_DIFEREN_PRESSAO_PRINCIPAL>
        <INST_DIFEREN_PRESSAO_PRINCIPAL>
          <NUM_SERIE>9225028</NUM_SERIE>
          <MED_PRSO_LIMITE_SPRR_ALRME>000022,500</MED_PRSO_LIMITE_SPRR_ALRME>
          <MED_PRSO_LMTE_INFRR_ALRME>000002,500</MED_PRSO_LMTE_INFRR_ALRME>
          <IND_HABILITACAO_ALARME>S</IND_HABILITACAO_ALARME>
          <MED_PRSO_ADOTADA_FALHA>000000,000</MED_PRSO_ADOTADA_FALHA>
          <DSC_ESTADO_INSNO_CASO_FALHA>Use last hour's average on transmitter fail</DSC_ESTADO_INSNO_CASO_FALHA>
          <MED_CUTOFF_KPA>000000,120</MED_CUTOFF_KPA>
        </INST_DIFEREN_PRESSAO_PRINCIPAL>
      </LISTA_INST_DIFEREN_PRESSAO_PRINCIPAL>
      <LISTA_PRODUCAO>
        <PRODUCAO>
          <DHA_INICIO_PERIODO_MEDICAO>30/01/2023 00:00:00</DHA_INICIO_PERIODO_MEDICAO>
          <DHA_FIM_PERIODO_MEDICAO>31/01/2023 00:00:00</DHA_FIM_PERIODO_MEDICAO>
          <MED_DIFERENCIAL_PRESSAO>000000,000</MED_DIFERENCIAL_PRESSAO>
          <MED_PRESSAO_ESTATICA>000000,000</MED_PRESSAO_ESTATICA>
          <MED_TEMPERATURA>000,00</MED_TEMPERATURA>
          <PRZ_DURACAO_FLUXO_EFETIVO>0000,0000</PRZ_DURACAO_FLUXO_EFETIVO>
          <MED_CORRIGIDO_MVMDO>000000,00000</MED_CORRIGIDO_MVMDO>
        </PRODUCAO>
      </LISTA_PRODUCAO>
    </DADOS_BASICOS>
  </LISTA_DADOS_BASICOS>
  <DADOS_ADICIONAIS_GERACAO_XML>
    <VERSAO_GERADOR>Strack XML Driver - FPSO OSX-3 - Ver 1.0</VERSAO_GERADOR>
    <NOME_MAQUINA>OSX-3-CLIENT</NOME_MAQUINA>
    <ENDERECO_IP>169.254.103.179
10.13.3.48
10.0.1.21
::1
127.0.0.1
</ENDERECO_IP>
    <ENDERECO_MAC>00FF0BA48CB3
6805CA1506BD
10604B74634C

00000000000000E0
00000000000000E0
00000000000000E0
00000000000000E0
00000000000000E0
</ENDERECO_MAC>
  </DADOS_ADICIONAIS_GERACAO_XML>
</a003>